epa_regions/__init__.py
epa_regions/__main__.py
epa_regions/load.py
epa_regions/py.typed
epa_regions-0.0.5.dist-info/licenses/LICENSE
epa_regions-0.0.5.dist-info/WHEEL
epa_regions-0.0.5.dist-info/METADATA
epa_regions-0.0.5.dist-info/RECORD
