Metadata-Version: 2.4
Name: epa-regions
Version: 0.0.5
Summary: EPA region definitions and representations in
Author-email: zmoon <zmoon92@gmail.com>
Requires-Python: ~=3.8
License-File: LICENSE
Project-URL: Home, https://github.com/zmoon/epa-regions-python
Project-URL: Source, https://github.com/zmoon/epa-regions-python
